Metadata-Version: 2.1
Name: mvr
Version: 0.0.2
Summary: minimum violations ranking
Home-page: UNKNOWN
Author: Hunter Wapman
Author-email: hunter.wapman@gmail.com
License: UNKNOWN
Platform: UNKNOWN
Classifier: Programming Language :: Python :: 3
Classifier: License :: OSI Approved :: GNU General Public License v3 or later (GPLv3+)
Classifier: Operating System :: OS Independent
Classifier: Natural Language :: English
